{
  "Type": "Simple",
  "Effects": {
    "ItemPlayerAnimationsId": "Golem_Crystal_Earth_Default",
    "ItemAnimationId": "Spin"
  },
  "$Comment": "Prepare Delay",
  "RunTime": 0.717,
  "Next": {
    "Type": "Parallel",
    "$Comment": "Make sure this parallel interaction is needed and can\u0027t be optimized away",
    "Interactions": [
      {
        "Interactions": [
          {
            "Type": "Selector",
            "$Comment": "Length of Combat",
            "RunTime": 0.25,
            "Selector": {
              "Id": "Horizontal",
              "Direction": "ToLeft",
              "TestLineOfSight": true,
              "ExtendTop": 0,
              "ExtendBottom": 2,
              "StartDistance": 0.5,
              "EndDistance": 3.25,
              "Length": 360,
              "RollOffset": 0,
              "YawStartOffset": -90
            },
            "Next": {
              "Type": "Selector",
              "$Comment": "Length of Combat",
              "RunTime": 0.25,
              "Selector": {
                "Id": "Horizontal",
                "Direction": "ToLeft",
                "TestLineOfSight": true,
                "ExtendTop": 0,
                "ExtendBottom": 2,
                "StartDistance": 0.5,
                "EndDistance": 3.25,
                "Length": 360,
                "RollOffset": 0,
                "YawStartOffset": -90
              },
              "HitEntity": {
                "Interactions": [
                  {
                    "Type": "Replace",
                    "DefaultValue": {
                      "Interactions": [
                        "Golem_Flame_Spin_Damage"
                      ]
                    },
                    "Var": "Spin_Damage",
                    "Effects": {
                      "WorldSoundEventId": "SFX_Bomb_Fire_Goblin_Death",
                      "Particles": [
                        {
                          "PositionOffset": {
                            "X": 0,
                            "Y": 0,
                            "Z": 3
                          },
                          "TargetEntityPart": "Entity",
                          "SystemId": "Explosion_Big"
                        }
                      ]
                    }
                  }
                ]
              }
            },
            "HitEntity": {
              "Interactions": [
                {
                  "Type": "Replace",
                  "DefaultValue": {
                    "Interactions": [
                      "Golem_Flame_Spin_Damage"
                    ]
                  },
                  "Var": "Spin_Damage",
                  "Effects": {
                    "WorldSoundEventId": "SFX_Bomb_Fire_Goblin_Death",
                    "Particles": [
                      {
                        "PositionOffset": {
                          "X": 0,
                          "Y": 0,
                          "Z": 3
                        },
                        "TargetEntityPart": "Entity",
                        "SystemId": "Explosion_Big"
                      }
                    ]
                  }
                }
              ]
            }
          }
        ]
      },
      {
        "Interactions": [
          {
            "Type": "Simple",
            "$Comment": "Length of Effect",
            "RunTime": 0.617,
            "Effects": {
              "WorldSoundEventId": "SFX_Golem_Earth_Swing"
            }
          }
        ]
      }
    ]
  }
}